dicomweb_client/__init__.py
dicomweb_client/api.py
dicomweb_client/cli.py
dicomweb_client/file.py
dicomweb_client/log.py
dicomweb_client/protocol.py
dicomweb_client/py.typed
dicomweb_client/session_utils.py
dicomweb_client/uri.py
dicomweb_client/web.py
dicomweb_client/ext/__init__.py
dicomweb_client/ext/gcp/__init__.py
dicomweb_client/ext/gcp/session_utils.py
dicomweb_client/ext/gcp/uri.py
dicomweb_client-0.60.0.dist-info/METADATA
dicomweb_client-0.60.0.dist-info/WHEEL
dicomweb_client-0.60.0.dist-info/entry_points.txt
dicomweb_client-0.60.0.dist-info/licenses/LICENSE
dicomweb_client-0.60.0.dist-info/RECORD
