Metadata-Version: 2.4
Name: dicomweb-client
Version: 0.60.0
Summary: Client for DICOMweb RESTful services.
Project-URL: homepage, https://github.com/imagingdatacommons/dicomweb-client
Project-URL: documentation, https://dicomweb-client.readthedocs.io/
Project-URL: repository, https://github.com/ImagingDataCommons/dicomweb-client.git
Author: Markus D. Herrmann
Maintainer: Markus D. Herrmann, Christopher P. Bridge, Steve Pieper
License: LICENSE
License-File: LICENSE
Classifier: Environment :: Web Environment
Classifier: Intended Audience :: Science/Research
Classifier: License :: OSI Approved :: MIT License
Classifier: Operating System :: MacOS
Classifier: Operating System :: Microsoft :: Windows
Classifier: Operating System :: POSIX :: Linux
Classifier: Programming Language :: Python :: 3
Classifier: Programming Language :: Python :: 3.9
Classifier: Programming Language :: Python :: 3.10
Classifier: Programming Language :: Python :: 3.11
Classifier: Programming Language :: Python :: 3.12
Classifier: Programming Language :: Python :: 3.13
Classifier: Topic :: Internet :: WWW/HTTP
Classifier: Topic :: Multimedia :: Graphics
Classifier: Topic :: Scientific/Engineering :: Information Analysis
Requires-Python: >=3.9
Requires-Dist: numpy>=1.19
Requires-Dist: pillow>=8.3
Requires-Dist: pydicom>=2.2
Requires-Dist: requests>=2.18
Requires-Dist: retrying>=1.3.3
Requires-Dist: typing-extensions>=4.0; python_version < '3.8.0'
Provides-Extra: gcp
Requires-Dist: dataclasses>=0.8; (python_version == '3.6') and extra == 'gcp'
Requires-Dist: google-auth>=1.6; extra == 'gcp'
